Classfile /E:/java8/eclipse/workspace/java8/target/classes/h4/java6/enu/Week.class
  Last modified 2017-11-11; size 2040 bytes
  MD5 checksum 26d620de651721722bdb35bf066cf381
  Compiled from "Week.java"
public final class h4.java6.enu.Week extends java.lang.Enum<h4.java6.enu.Week>
  minor version: 0
  major version: 49
  flags: ACC_PUBLIC, ACC_FINAL, ACC_SUPER, ACC_ENUM
Constant pool:
    #1 = Class              #2            // h4/java6/enu/Week
    #2 = Utf8               h4/java6/enu/Week
    #3 = Class              #4            // java/lang/Enum
    #4 = Utf8               java/lang/Enum
    #5 = Utf8               MON
    #6 = Utf8               Lh4/java6/enu/Week;
    #7 = Utf8               TUES
    #8 = Utf8               WED
    #9 = Utf8               THUR
   #10 = Utf8               FRI
   #11 = Utf8               SAT
   #12 = Utf8               SUN
   #13 = Utf8               cnDay
   #14 = Utf8               Ljava/lang/String;
   #15 = Utf8               usDay
   #16 = Utf8               ENUM$VALUES
   #17 = Utf8               [Lh4/java6/enu/Week;
   #18 = Utf8               <clinit>
   #19 = Utf8               ()V
   #20 = Utf8               Code
   #21 = String             #5            // MON
   #22 = String             #23           // 星期一
   #23 = Utf8               星期一
   #24 = String             #25           // Monday
   #25 = Utf8               Monday
   #26 = Methodref          #1.#27        // h4/java6/enu/Week."<init>":(Ljava/lang/String;ILjava/lang/String;Ljava/lang/String;)V
   #27 = NameAndType        #28:#29       // "<init>":(Ljava/lang/String;ILjava/lang/String;Ljava/lang/String;)V
   #28 = Utf8               <init>
   #29 = Utf8               (Ljava/lang/String;ILjava/lang/String;Ljava/lang/String;)V
   #30 = Fieldref           #1.#31        // h4/java6/enu/Week.MON:Lh4/java6/enu/Week;
   #31 = NameAndType        #5:#6         // MON:Lh4/java6/enu/Week;
   #32 = String             #7            // TUES
   #33 = String             #34           // 星期二
   #34 = Utf8               星期二
   #35 = String             #36           // Tuesday
   #36 = Utf8               Tuesday
   #37 = Fieldref           #1.#38        // h4/java6/enu/Week.TUES:Lh4/java6/enu/Week;
   #38 = NameAndType        #7:#6         // TUES:Lh4/java6/enu/Week;
   #39 = String             #8            // WED
   #40 = String             #41           // 星期三
   #41 = Utf8               星期三
   #42 = String             #43           // Wednesday
   #43 = Utf8               Wednesday
   #44 = Fieldref           #1.#45        // h4/java6/enu/Week.WED:Lh4/java6/enu/Week;
   #45 = NameAndType        #8:#6         // WED:Lh4/java6/enu/Week;
   #46 = String             #9            // THUR
   #47 = String             #48           // 星期四
   #48 = Utf8               星期四
   #49 = String             #50           // Thursday
   #50 = Utf8               Thursday
   #51 = Fieldref           #1.#52        // h4/java6/enu/Week.THUR:Lh4/java6/enu/Week;
   #52 = NameAndType        #9:#6         // THUR:Lh4/java6/enu/Week;
   #53 = String             #10           // FRI
   #54 = String             #55           // 星期五
   #55 = Utf8               星期五
   #56 = String             #57           // Friday
   #57 = Utf8               Friday
   #58 = Fieldref           #1.#59        // h4/java6/enu/Week.FRI:Lh4/java6/enu/Week;
   #59 = NameAndType        #10:#6        // FRI:Lh4/java6/enu/Week;
   #60 = String             #11           // SAT
   #61 = String             #62           // 星期六
   #62 = Utf8               星期六
   #63 = String             #64           // Saturday
   #64 = Utf8               Saturday
   #65 = Fieldref           #1.#66        // h4/java6/enu/Week.SAT:Lh4/java6/enu/Week;
   #66 = NameAndType        #11:#6        // SAT:Lh4/java6/enu/Week;
   #67 = String             #12           // SUN
   #68 = String             #69           // 星期日
   #69 = Utf8               星期日
   #70 = String             #71           // Sunday
   #71 = Utf8               Sunday
   #72 = Fieldref           #1.#73        // h4/java6/enu/Week.SUN:Lh4/java6/enu/Week;
   #73 = NameAndType        #12:#6        // SUN:Lh4/java6/enu/Week;
   #74 = Fieldref           #1.#75        // h4/java6/enu/Week.ENUM$VALUES:[Lh4/java6/enu/Week;
   #75 = NameAndType        #16:#17       // ENUM$VALUES:[Lh4/java6/enu/Week;
   #76 = Utf8               LineNumberTable
   #77 = Utf8               LocalVariableTable
   #78 = Methodref          #3.#79        // java/lang/Enum."<init>":(Ljava/lang/String;I)V
   #79 = NameAndType        #28:#80       // "<init>":(Ljava/lang/String;I)V
   #80 = Utf8               (Ljava/lang/String;I)V
   #81 = Fieldref           #1.#82        // h4/java6/enu/Week.cnDay:Ljava/lang/String;
   #82 = NameAndType        #13:#14       // cnDay:Ljava/lang/String;
   #83 = Fieldref           #1.#84        // h4/java6/enu/Week.usDay:Ljava/lang/String;
   #84 = NameAndType        #15:#14       // usDay:Ljava/lang/String;
   #85 = Utf8               this
   #86 = Utf8               getCnDay
   #87 = Utf8               ()Ljava/lang/String;
   #88 = Utf8               getUsDay
   #89 = Utf8               toString
   #90 = Class              #91           // java/lang/StringBuilder
   #91 = Utf8               java/lang/StringBuilder
   #92 = String             #93           // English is
   #93 = Utf8               English is
   #94 = Methodref          #90.#95       // java/lang/StringBuilder."<init>":(Ljava/lang/String;)V
   #95 = NameAndType        #28:#96       // "<init>":(Ljava/lang/String;)V
   #96 = Utf8               (Ljava/lang/String;)V
   #97 = Methodref          #90.#98       // java/lang/StringBuilder.append:(Ljava/lang/String;)Ljava/lang/StringBuilder;
   #98 = NameAndType        #99:#100      // append:(Ljava/lang/String;)Ljava/lang/StringBuilder;
   #99 = Utf8               append
  #100 = Utf8               (Ljava/lang/String;)Ljava/lang/StringBuilder;
  #101 = String             #102          // , 中文是
  #102 = Utf8               , 中文是
  #103 = Methodref          #90.#104      // java/lang/StringBuilder.toString:()Ljava/lang/String;
  #104 = NameAndType        #89:#87       // toString:()Ljava/lang/String;
  #105 = Utf8               values
  #106 = Utf8               ()[Lh4/java6/enu/Week;
  #107 = Methodref          #108.#110     // java/lang/System.arraycopy:(Ljava/lang/Object;ILjava/lang/Object;II)V
  #108 = Class              #109          // java/lang/System
  #109 = Utf8               java/lang/System
  #110 = NameAndType        #111:#112     // arraycopy:(Ljava/lang/Object;ILjava/lang/Object;II)V
  #111 = Utf8               arraycopy
  #112 = Utf8               (Ljava/lang/Object;ILjava/lang/Object;II)V
  #113 = Utf8               valueOf
  #114 = Utf8               (Ljava/lang/String;)Lh4/java6/enu/Week;
  #115 = Methodref          #3.#116       // java/lang/Enum.valueOf:(Ljava/lang/Class;Ljava/lang/String;)Ljava/lang/Enum;
  #116 = NameAndType        #113:#117     // valueOf:(Ljava/lang/Class;Ljava/lang/String;)Ljava/lang/Enum;
  #117 = Utf8               (Ljava/lang/Class;Ljava/lang/String;)Ljava/lang/Enum;
  #118 = Utf8               SourceFile
  #119 = Utf8               Week.java
  #120 = Utf8               Signature
  #121 = Utf8               Ljava/lang/Enum<Lh4/java6/enu/Week;>;
{
  public static final h4.java6.enu.Week MON;
    descriptor: Lh4/java6/enu/Week;
    flags: ACC_PUBLIC, ACC_STATIC, ACC_FINAL, ACC_ENUM

  public static final h4.java6.enu.Week TUES;
    descriptor: Lh4/java6/enu/Week;
    flags: ACC_PUBLIC, ACC_STATIC, ACC_FINAL, ACC_ENUM

  public static final h4.java6.enu.Week WED;
    descriptor: Lh4/java6/enu/Week;
    flags: ACC_PUBLIC, ACC_STATIC, ACC_FINAL, ACC_ENUM

  public static final h4.java6.enu.Week THUR;
    descriptor: Lh4/java6/enu/Week;
    flags: ACC_PUBLIC, ACC_STATIC, ACC_FINAL, ACC_ENUM

  public static final h4.java6.enu.Week FRI;
    descriptor: Lh4/java6/enu/Week;
    flags: ACC_PUBLIC, ACC_STATIC, ACC_FINAL, ACC_ENUM

  public static final h4.java6.enu.Week SAT;
    descriptor: Lh4/java6/enu/Week;
    flags: ACC_PUBLIC, ACC_STATIC, ACC_FINAL, ACC_ENUM

  public static final h4.java6.enu.Week SUN;
    descriptor: Lh4/java6/enu/Week;
    flags: ACC_PUBLIC, ACC_STATIC, ACC_FINAL, ACC_ENUM

  static {};
    descriptor: ()V
    flags: ACC_STATIC
    Code:
      stack=6, locals=0, args_size=0
         0: new           #1                  // class h4/java6/enu/Week
         3: dup
         4: ldc           #21                 // String MON
         6: iconst_0
         7: ldc           #22                 // String 星期一
         9: ldc           #24                 // String Monday
        11: invokespecial #26                 // Method "<init>":(Ljava/lang/String;ILjava/lang/String;Ljava/lang/String;)V
        14: putstatic     #30                 // Field MON:Lh4/java6/enu/Week;
        17: new           #1                  // class h4/java6/enu/Week
        20: dup
        21: ldc           #32                 // String TUES
        23: iconst_1
        24: ldc           #33                 // String 星期二
        26: ldc           #35                 // String Tuesday
        28: invokespecial #26                 // Method "<init>":(Ljava/lang/String;ILjava/lang/String;Ljava/lang/String;)V
        31: putstatic     #37                 // Field TUES:Lh4/java6/enu/Week;
        34: new           #1                  // class h4/java6/enu/Week
        37: dup
        38: ldc           #39                 // String WED
        40: iconst_2
        41: ldc           #40                 // String 星期三
        43: ldc           #42                 // String Wednesday
        45: invokespecial #26                 // Method "<init>":(Ljava/lang/String;ILjava/lang/String;Ljava/lang/String;)V
        48: putstatic     #44                 // Field WED:Lh4/java6/enu/Week;
        51: new           #1                  // class h4/java6/enu/Week
        54: dup
        55: ldc           #46                 // String THUR
        57: iconst_3
        58: ldc           #47                 // String 星期四
        60: ldc           #49                 // String Thursday
        62: invokespecial #26                 // Method "<init>":(Ljava/lang/String;ILjava/lang/String;Ljava/lang/String;)V
        65: putstatic     #51                 // Field THUR:Lh4/java6/enu/Week;
        68: new           #1                  // class h4/java6/enu/Week
        71: dup
        72: ldc           #53                 // String FRI
        74: iconst_4
        75: ldc           #54                 // String 星期五
        77: ldc           #56                 // String Friday
        79: invokespecial #26                 // Method "<init>":(Ljava/lang/String;ILjava/lang/String;Ljava/lang/String;)V
        82: putstatic     #58                 // Field FRI:Lh4/java6/enu/Week;
        85: new           #1                  // class h4/java6/enu/Week
        88: dup
        89: ldc           #60                 // String SAT
        91: iconst_5
        92: ldc           #61                 // String 星期六
        94: ldc           #63                 // String Saturday
        96: invokespecial #26                 // Method "<init>":(Ljava/lang/String;ILjava/lang/String;Ljava/lang/String;)V
        99: putstatic     #65                 // Field SAT:Lh4/java6/enu/Week;
       102: new           #1                  // class h4/java6/enu/Week
       105: dup
       106: ldc           #67                 // String SUN
       108: bipush        6
       110: ldc           #68                 // String 星期日
       112: ldc           #70                 // String Sunday
       114: invokespecial #26                 // Method "<init>":(Ljava/lang/String;ILjava/lang/String;Ljava/lang/String;)V
       117: putstatic     #72                 // Field SUN:Lh4/java6/enu/Week;
       120: bipush        7
       122: anewarray     #1                  // class h4/java6/enu/Week
       125: dup
       126: iconst_0
       127: getstatic     #30                 // Field MON:Lh4/java6/enu/Week;
       130: aastore
       131: dup
       132: iconst_1
       133: getstatic     #37                 // Field TUES:Lh4/java6/enu/Week;
       136: aastore
       137: dup
       138: iconst_2
       139: getstatic     #44                 // Field WED:Lh4/java6/enu/Week;
       142: aastore
       143: dup
       144: iconst_3
       145: getstatic     #51                 // Field THUR:Lh4/java6/enu/Week;
       148: aastore
       149: dup
       150: iconst_4
       151: getstatic     #58                 // Field FRI:Lh4/java6/enu/Week;
       154: aastore
       155: dup
       156: iconst_5
       157: getstatic     #65                 // Field SAT:Lh4/java6/enu/Week;
       160: aastore
       161: dup
       162: bipush        6
       164: getstatic     #72                 // Field SUN:Lh4/java6/enu/Week;
       167: aastore
       168: putstatic     #74                 // Field ENUM$VALUES:[Lh4/java6/enu/Week;
       171: return
      LineNumberTable:
        line 5: 0
        line 6: 17
        line 7: 34
        line 8: 51
        line 9: 68
        line 10: 85
        line 11: 102
        line 3: 120
      LocalVariableTable:
        Start  Length  Slot  Name   Signature

  public java.lang.String getCnDay();
    descriptor: ()Ljava/lang/String;
    flags: ACC_PUBLIC
    Code:
      stack=1, locals=1, args_size=1
         0: aload_0
         1: getfield      #81                 // Field cnDay:Ljava/lang/String;
         4: areturn
      LineNumberTable:
        line 22: 0
      LocalVariableTable:
        Start  Length  Slot  Name   Signature
            0       5     0  this   Lh4/java6/enu/Week;

  public java.lang.String getUsDay();
    descriptor: ()Ljava/lang/String;
    flags: ACC_PUBLIC
    Code:
      stack=1, locals=1, args_size=1
         0: aload_0
         1: getfield      #83                 // Field usDay:Ljava/lang/String;
         4: areturn
      LineNumberTable:
        line 26: 0
      LocalVariableTable:
        Start  Length  Slot  Name   Signature
            0       5     0  this   Lh4/java6/enu/Week;

  public java.lang.String toString();
    descriptor: ()Ljava/lang/String;
    flags: ACC_PUBLIC
    Code:
      stack=3, locals=1, args_size=1
         0: new           #90                 // class java/lang/StringBuilder
         3: dup
         4: ldc           #92                 // String English is
         6: invokespecial #94                 // Method java/lang/StringBuilder."<init>":(Ljava/lang/String;)V
         9: aload_0
        10: getfield      #83                 // Field usDay:Ljava/lang/String;
        13: invokevirtual #97                 // Method java/lang/StringBuilder.append:(Ljava/lang/String;)Ljava/lang/StringBuilder;
        16: ldc           #101                // String , 中文是
        18: invokevirtual #97                 // Method java/lang/StringBuilder.append:(Ljava/lang/String;)Ljava/lang/StringBuilder;
        21: aload_0
        22: getfield      #81                 // Field cnDay:Ljava/lang/String;
        25: invokevirtual #97                 // Method java/lang/StringBuilder.append:(Ljava/lang/String;)Ljava/lang/StringBuilder;
        28: invokevirtual #103                // Method java/lang/StringBuilder.toString:()Ljava/lang/String;
        31: areturn
      LineNumberTable:
        line 31: 0
      LocalVariableTable:
        Start  Length  Slot  Name   Signature
            0      32     0  this   Lh4/java6/enu/Week;

  public static h4.java6.enu.Week[] values();
    descriptor: ()[Lh4/java6/enu/Week;
    flags: ACC_PUBLIC, ACC_STATIC
    Code:
      stack=5, locals=3, args_size=0
         0: getstatic     #74                 // Field ENUM$VALUES:[Lh4/java6/enu/Week;
         3: dup
         4: astore_0
         5: iconst_0
         6: aload_0
         7: arraylength
         8: dup
         9: istore_1
        10: anewarray     #1                  // class h4/java6/enu/Week
        13: dup
        14: astore_2
        15: iconst_0
        16: iload_1
        17: invokestatic  #107                // Method java/lang/System.arraycopy:(Ljava/lang/Object;ILjava/lang/Object;II)V
        20: aload_2
        21: areturn
      LineNumberTable:
        line 1: 0
      LocalVariableTable:
        Start  Length  Slot  Name   Signature

  public static h4.java6.enu.Week valueOf(java.lang.String);
    descriptor: (Ljava/lang/String;)Lh4/java6/enu/Week;
    flags: ACC_PUBLIC, ACC_STATIC
    Code:
      stack=2, locals=1, args_size=1
         0: ldc           #1                  // class h4/java6/enu/Week
         2: aload_0
         3: invokestatic  #115                // Method java/lang/Enum.valueOf:(Ljava/lang/Class;Ljava/lang/String;)Ljava/lang/Enum;
         6: checkcast     #1                  // class h4/java6/enu/Week
         9: areturn
      LineNumberTable:
        line 1: 0
      LocalVariableTable:
        Start  Length  Slot  Name   Signature
}
SourceFile: "Week.java"
Signature: #121                         // Ljava/lang/Enum<Lh4/java6/enu/Week;>;
